getdents/__about__.py
getdents/__init__.py
getdents/__main__.py
getdents/_getdents.abi3.so
getdents/_getdents.c
getdents/_getdents.pyi
getdents/cli.py
getdents/formatters.py
getdents/py.typed
getdents-1.0.0.dist-info/METADATA
getdents-1.0.0.dist-info/WHEEL
getdents-1.0.0.dist-info/entry_points.txt
getdents-1.0.0.dist-info/top_level.txt
getdents-1.0.0.dist-info/RECORD
getdents-1.0.0.dist-info/licenses/LICENSE
