Metadata-Version: 2.4
Name: getdents
Version: 1.0.0
Summary: Python binding to linux syscall getdents64.
Author-email: ZipFile <zipfile.d@protonmail.com>
License-Expression: BSD-2-Clause
Project-URL: Source, https://github.com/ZipFile/python-getdents
Keywords: getdents
Classifier: Operating System :: POSIX :: Linux
Classifier: Programming Language :: Python :: 3
Classifier: Programming Language :: Python :: Implementation :: CPython
Classifier: Programming Language :: Python :: Free Threading :: 2 - Beta
Classifier: Topic :: System :: Filesystems
Requires-Python: >=3.10
License-File: LICENSE
Provides-Extra: dev
Requires-Dist: flake8; extra == "dev"
Requires-Dist: flake8-pyproject; extra == "dev"
Requires-Dist: isort; extra == "dev"
Requires-Dist: mypy; extra == "dev"
Requires-Dist: pytest; extra == "dev"
Requires-Dist: pytest-cov; extra == "dev"
Dynamic: license-file
